model_tracker/__init__.py
model_tracker/tracker.py
cloudframe-0.0.1.dist-info/METADATA
cloudframe-0.0.1.dist-info/WHEEL
cloudframe-0.0.1.dist-info/top_level.txt
cloudframe-0.0.1.dist-info/RECORD
