Metadata-Version: 2.1
Name: cloudframe
Version: 0.0.1
Summary: A light set of supporting modules to assist the data science workflow based on Cloudframe's proprietary data science enablers
Home-page: https://github.com/cloudframe/cloudframe
Author: Cloudframe Analytics
Author-email: info@cloudframe.io
License: MIT
Platform: UNKNOWN
Classifier: License :: OSI Approved :: MIT License
Classifier: Programming Language :: Python :: 3
Classifier: Programming Language :: Python :: 3.7
Requires-Dist: json
Requires-Dist: pickle
Requires-Dist: pyyaml
